zztoolbox/__init__.py
zztoolbox/image.py
zztoolbox/render.py
zztoolbox/tensor.py
zztoolbox/visual/__init__.py
zztoolbox/visual/matplot_utils.py
zztoolbox/visual/plot_embbed.py
zztoolbox-0.0.3.dist-info/METADATA
zztoolbox-0.0.3.dist-info/WHEEL
zztoolbox-0.0.3.dist-info/licenses/LICENSE
zztoolbox-0.0.3.dist-info/RECORD
