Metadata-Version: 2.1
Name: zztoolbox
Version: 0.0.3
Summary: base function
Project-URL: Homepage, https://github.com/jwzxgy2007/zztoolbox
Project-URL: Bug Tracker, https://github.com/jwzxgy2007/zztoolbox/issues
Author-email: Lingxiao Zhang <zhanglingxiao@ict.ac.cn>
License-File: LICENSE
Classifier: License :: OSI Approved :: MIT License
Classifier: Operating System :: OS Independent
Classifier: Programming Language :: Python :: 3
Requires-Python: >=3.8
